MisER/__init__.py
MisER/block_class.py
MisER/find_small_exon.py
MisER/fix_small_exon_multiproc.py
MisER/run_miser.py
MisER/version.py
MisER-1.0.0.dist-info/LICENSE
MisER-1.0.0.dist-info/METADATA
MisER-1.0.0.dist-info/WHEEL
MisER-1.0.0.dist-info/entry_points.txt
MisER-1.0.0.dist-info/top_level.txt
MisER-1.0.0.dist-info/RECORD
