Metadata-Version: 2.1
Name: MisER
Version: 1.0.0
Summary: Find and fix missed small exons.
Home-page: https://github.com/zhenLiuXplr/MisER-project
Author: Zhen Liu
Author-email: liuzhen_sirius@outlook.com
Classifier: Programming Language :: Python :: 3
Classifier: License :: OSI Approved :: MIT License
Classifier: Operating System :: POSIX :: Linux
Requires-Python: >=3
License-File: LICENSE
Requires-Dist: numpy
Requires-Dist: pandas (<2.0.0)
Requires-Dist: pysam
Requires-Dist: parasail (>=1.1.17)
